telegram_bot_reporter/__init__.py
telegram_bot_reporter/core/__init__.py
telegram_bot_reporter/core/async_bot.py
telegram_bot_reporter/core/base_bot.py
telegram_bot_reporter/core/sync_bot.py
telegram_bot_reporter-0.2.3.dist-info/LICENSE
telegram_bot_reporter-0.2.3.dist-info/METADATA
telegram_bot_reporter-0.2.3.dist-info/WHEEL
telegram_bot_reporter-0.2.3.dist-info/RECORD
