Metadata-Version: 2.1
Name: telegram-bot-reporter
Version: 0.2.3
Summary: Library for sending messages and files using a Telegram bot.
Home-page: https://pypi.org/project/telegram-bot-reporter
License: MIT
Author: deskent
Author-email: battenetciz@gmail.com
Requires-Python: >=3.10,<4.0
Classifier: License :: OSI Approved :: MIT License
Classifier: Programming Language :: Python :: 3
Classifier: Programming Language :: Python :: 3.10
Classifier: Programming Language :: Python :: 3.11
Classifier: Programming Language :: Python :: 3.12
Classifier: Programming Language :: Python :: 3.13
Requires-Dist: httpx (>=0.24.1)
Project-URL: Repository, https://github.com/Deskent/bot_reporter
